btcagent/__init__.py
btcagent-0.0.13.dist-info/LICENSE
btcagent-0.0.13.dist-info/METADATA
btcagent-0.0.13.dist-info/WHEEL
btcagent-0.0.13.dist-info/top_level.txt
btcagent-0.0.13.dist-info/RECORD
